[
  {
    "Unit": "Aventurine",
    "Element": "Imaginary",
    "Path": "Preservation",
    "Rarity": 5,
    "BaseHP": 1203,
    "BaseATK": 446,
    "BaseDEF": 655,
    "BaseSpeed": 106,
    "UltCost": "110"
  },
  {
    "Unit": "Fu Xuan",
    "Element": "Quantum",
    "Path": "Preservation",
    "Rarity": 5,
    "BaseHP": 1474,
    "BaseATK": 465,
    "BaseDEF": 606,
    "BaseSpeed": 100,
    "UltCost": "135"
  },
  {
    "Unit": "Sparkle",
    "Element": "Quantum",
    "Path": "Harmony",
    "Rarity": 5,
    "BaseHP": 1397,
    "BaseATK": 523,
    "BaseDEF": 485,
    "BaseSpeed": 101,
    "UltCost": "110"
  },
  {
    "Unit": "Blade",
    "Element": "Wind",
    "Path": "Destruction",
    "Rarity": 5,
    "BaseHP": 1358,
    "BaseATK": 543,
    "BaseDEF": 485,
    "BaseSpeed": 97,
    "UltCost": "130"
  },
  {
    "Unit": "Gepard",
    "Element": "Ice",
    "Path": "Preservation",
    "Rarity": 5,
    "BaseHP": 1397,
    "BaseATK": 543,
    "BaseDEF": 654,
    "BaseSpeed": 92,
    "UltCost": "100"
  },
  {
    "Unit": "Bailu",
    "Element": "Lightning",
    "Path": "Abundance",
    "Rarity": 5,
    "BaseHP": 1319,
    "BaseATK": 562,
    "BaseDEF": 485,
    "BaseSpeed": 98,
    "UltCost": "100"
  },
  {
    "Unit": "Bronya",
    "Element": "Wind",
    "Path": "Harmony",
    "Rarity": 5,
    "BaseHP": 1241,
    "BaseATK": 582,
    "BaseDEF": 533,
    "BaseSpeed": 99,
    "UltCost": "120"
  },
  {
    "Unit": "Huohuo",
    "Element": "Wind",
    "Path": "Abundance",
    "Rarity": 5,
    "BaseHP": 1358,
    "BaseATK": 601,
    "BaseDEF": 509,
    "BaseSpeed": 98,
    "UltCost": "140"
  },
  {
    "Unit": "Fire MC",
    "Element": "Fire",
    "Path": "Preservation",
    "Rarity": 5,
    "BaseHP": 1241,
    "BaseATK": 601,
    "BaseDEF": 606,
    "BaseSpeed": 95,
    "UltCost": "120"
  },
  {
    "Unit": "Topaz & Numby",
    "Element": "Fire",
    "Path": "Hunt",
    "Rarity": 5,
    "BaseHP": 931,
    "BaseATK": 620,
    "BaseDEF": 412,
    "BaseSpeed": 110,
    "UltCost": "130"
  },
  {
    "Unit": "Physical MC",
    "Element": "Physical",
    "Path": "Destruction",
    "Rarity": 5,
    "BaseHP": 1203,
    "BaseATK": 620,
    "BaseDEF": 460,
    "BaseSpeed": 100,
    "UltCost": "120"
  },
  {
    "Unit": "Welt",
    "Element": "Imaginary",
    "Path": "Nihility",
    "Rarity": 5,
    "BaseHP": 1125,
    "BaseATK": 621,
    "BaseDEF": 509,
    "BaseSpeed": 102,
    "UltCost": "120"
  },
  {
    "Unit": "Seele",
    "Element": "Quantum",
    "Path": "Hunt",
    "Rarity": 5,
    "BaseHP": 931,
    "BaseATK": 640,
    "BaseDEF": 363,
    "BaseSpeed": 115,
    "UltCost": "120"
  },
  {
    "Unit": "Silver Wolf",
    "Element": "Quantum",
    "Path": "Nihility",
    "Rarity": 5,
    "BaseHP": 1047,
    "BaseATK": 640,
    "BaseDEF": 460,
    "BaseSpeed": 107,
    "UltCost": "110"
  },
  {
    "Unit": "Ruan Mei",
    "Element": "Ice",
    "Path": "Harmony",
    "Rarity": 5,
    "BaseHP": 1086,
    "BaseATK": 659,
    "BaseDEF": 485,
    "BaseSpeed": 104,
    "UltCost": "130"
  },
  {
    "Unit": "Black Swan",
    "Element": "Wind",
    "Path": "Nihility",
    "Rarity": 5,
    "BaseHP": 1086,
    "BaseATK": 659,
    "BaseDEF": 485,
    "BaseSpeed": 102,
    "UltCost": "120"
  },
  {
    "Unit": "Yanqing",
    "Element": "Ice",
    "Path": "Hunt",
    "Rarity": 5,
    "BaseHP": 892,
    "BaseATK": 679,
    "BaseDEF": 412,
    "BaseSpeed": 109,
    "UltCost": "140"
  },
  {
    "Unit": "Kafka",
    "Element": "Lightning",
    "Path": "Nihility",
    "Rarity": 5,
    "BaseHP": 1086,
    "BaseATK": 679,
    "BaseDEF": 485,
    "BaseSpeed": 100,
    "UltCost": "120"
  },
  {
    "Unit": "Jingliu",
    "Element": "Ice",
    "Path": "Destruction",
    "Rarity": 5,
    "BaseHP": 1435,
    "BaseATK": 679,
    "BaseDEF": 485,
    "BaseSpeed": 96,
    "UltCost": "140"
  },
  {
    "Unit": "DanIL",
    "Element": "Imaginary",
    "Path": "Destruction",
    "Rarity": 5,
    "BaseHP": 1241,
    "BaseATK": 698,
    "BaseDEF": 363,
    "BaseSpeed": 102,
    "UltCost": "140"
  },
  {
    "Unit": "Jing Yuan",
    "Element": "Lightning",
    "Path": "Erudition",
    "Rarity": 5,
    "BaseHP": 1164,
    "BaseATK": 698,
    "BaseDEF": 485,
    "BaseSpeed": 99,
    "UltCost": "130"
  },
  {
    "Unit": "Acheron",
    "Element": "Lightning",
    "Path": "Nihility",
    "Rarity": 5,
    "BaseHP": 1125,
    "BaseATK": 699,
    "BaseDEF": 437,
    "BaseSpeed": 101,
    "UltCost": "9"
  },
  {
    "Unit": "Argenti",
    "Element": "Physical",
    "Path": "Erudition",
    "Rarity": 5,
    "BaseHP": 1047,
    "BaseATK": 737,
    "BaseDEF": 363,
    "BaseSpeed": 103,
    "UltCost": "90/180"
  },
  {
    "Unit": "Clara",
    "Element": "Physical",
    "Path": "Destruction",
    "Rarity": 5,
    "BaseHP": 1319,
    "BaseATK": 737,
    "BaseDEF": 485,
    "BaseSpeed": 90,
    "UltCost": "110"
  },
  {
    "Unit": "Luocha",
    "Element": "Imaginary",
    "Path": "Abundance",
    "Rarity": 5,
    "BaseHP": 1280,
    "BaseATK": 756,
    "BaseDEF": 363,
    "BaseSpeed": 101,
    "UltCost": "100"
  },
  {
    "Unit": "Himeko",
    "Element": "Fire",
    "Path": "Erudition",
    "Rarity": 5,
    "BaseHP": 1047,
    "BaseATK": 756,
    "BaseDEF": 436,
    "BaseSpeed": 96,
    "UltCost": "120"
  },
  {
    "Unit": "Dr. Ratio",
    "Element": "Imaginary",
    "Path": "Hunt",
    "Rarity": 5,
    "BaseHP": 1047,
    "BaseATK": 776,
    "BaseDEF": 460,
    "BaseSpeed": 103,
    "UltCost": "140"
  },
  {
    "Unit": "Natasha",
    "Element": "Physical",
    "Path": "Abundance",
    "Rarity": 4,
    "BaseHP": 1164,
    "BaseATK": 476,
    "BaseDEF": 507,
    "BaseSpeed": 98,
    "UltCost": "90"
  },
  {
    "Unit": "Lynx",
    "Element": "Quantum",
    "Path": "Abundance",
    "Rarity": 4,
    "BaseHP": 1058,
    "BaseATK": 493,
    "BaseDEF": 551,
    "BaseSpeed": 100,
    "UltCost": "100"
  },
  {
    "Unit": "March 7th",
    "Element": "Ice",
    "Path": "Preservation",
    "Rarity": 4,
    "BaseHP": 1058,
    "BaseATK": 511,
    "BaseDEF": 573,
    "BaseSpeed": 101,
    "UltCost": "120"
  },
  {
    "Unit": "Asta",
    "Element": "Fire",
    "Path": "Harmony",
    "Rarity": 4,
    "BaseHP": 1023,
    "BaseATK": 512,
    "BaseDEF": 463,
    "BaseSpeed": 106,
    "UltCost": "120"
  },
  {
    "Unit": "Tingyun",
    "Element": "Lightning",
    "Path": "Harmony",
    "Rarity": 4,
    "BaseHP": 846,
    "BaseATK": 529,
    "BaseDEF": 396,
    "BaseSpeed": 112,
    "UltCost": "130"
  },
  {
    "Unit": "Gallagher",
    "Element": "Fire",
    "Path": "Abundance",
    "Rarity": 4,
    "BaseHP": 1305,
    "BaseATK": 529,
    "BaseDEF": 441,
    "BaseSpeed": 98,
    "UltCost": "110"
  },
  {
    "Unit": "Dan Heng",
    "Element": "Wind",
    "Path": "Hunt",
    "Rarity": 4,
    "BaseHP": 882,
    "BaseATK": 546,
    "BaseDEF": 396,
    "BaseSpeed": 110,
    "UltCost": "100"
  },
  {
    "Unit": "Pela",
    "Element": "Ice",
    "Path": "Nihility",
    "Rarity": 4,
    "BaseHP": 987,
    "BaseATK": 546,
    "BaseDEF": 463,
    "BaseSpeed": 105,
    "UltCost": "110"
  },
  {
    "Unit": "Hanya",
    "Element": "Physical",
    "Path": "Harmony",
    "Rarity": 4,
    "BaseHP": 917,
    "BaseATK": 564,
    "BaseDEF": 352,
    "BaseSpeed": 110,
    "UltCost": "140"
  },
  {
    "Unit": "Sushang",
    "Element": "Physical",
    "Path": "Hunt",
    "Rarity": 4,
    "BaseHP": 917,
    "BaseATK": 564,
    "BaseDEF": 418,
    "BaseSpeed": 107,
    "UltCost": "120"
  },
  {
    "Unit": "Guinaifen",
    "Element": "Fire",
    "Path": "Nihility",
    "Rarity": 4,
    "BaseHP": 882,
    "BaseATK": 582,
    "BaseDEF": 441,
    "BaseSpeed": 106,
    "UltCost": "120"
  },
  {
    "Unit": "Luka",
    "Element": "Physical",
    "Path": "Nihility",
    "Rarity": 4,
    "BaseHP": 917,
    "BaseATK": 582,
    "BaseDEF": 485,
    "BaseSpeed": 103,
    "UltCost": "130"
  },
  {
    "Unit": "Herta",
    "Element": "Ice",
    "Path": "Erudition",
    "Rarity": 4,
    "BaseHP": 952,
    "BaseATK": 582,
    "BaseDEF": 396,
    "BaseSpeed": 100,
    "UltCost": "110"
  },
  {
    "Unit": "Yukong",
    "Element": "Imaginary",
    "Path": "Harmony",
    "Rarity": 4,
    "BaseHP": 917,
    "BaseATK": 599,
    "BaseDEF": 374,
    "BaseSpeed": 107,
    "UltCost": "130"
  },
  {
    "Unit": "Xueyi",
    "Element": "Quantum",
    "Path": "Destruction",
    "Rarity": 4,
    "BaseHP": 1058,
    "BaseATK": 599,
    "BaseDEF": 396,
    "BaseSpeed": 103,
    "UltCost": "120"
  },
  {
    "Unit": "Arlan",
    "Element": "Lightning",
    "Path": "Destruction",
    "Rarity": 4,
    "BaseHP": 1199,
    "BaseATK": 599,
    "BaseDEF": 330,
    "BaseSpeed": 102,
    "UltCost": "110"
  },
  {
    "Unit": "Misha",
    "Element": "Ice",
    "Path": "Destruction",
    "Rarity": 4,
    "BaseHP": 1270,
    "BaseATK": 599,
    "BaseDEF": 396,
    "BaseSpeed": 96,
    "UltCost": "100"
  },
  {
    "Unit": "Sampo",
    "Element": "Wind",
    "Path": "Nihility",
    "Rarity": 4,
    "BaseHP": 1023,
    "BaseATK": 617,
    "BaseDEF": 396,
    "BaseSpeed": 102,
    "UltCost": "120"
  },
  {
    "Unit": "Hook",
    "Element": "Fire",
    "Path": "Destruction",
    "Rarity": 4,
    "BaseHP": 1340,
    "BaseATK": 617,
    "BaseDEF": 352,
    "BaseSpeed": 94,
    "UltCost": "120"
  },
  {
    "Unit": "Serval",
    "Element": "Lightning",
    "Path": "Erudition",
    "Rarity": 4,
    "BaseHP": 917,
    "BaseATK": 652,
    "BaseDEF": 374,
    "BaseSpeed": 104,
    "UltCost": "100"
  },
  {
    "Unit": "Qingque",
    "Element": "Quantum",
    "Path": "Erudition",
    "Rarity": 4,
    "BaseHP": 1023,
    "BaseATK": 652,
    "BaseDEF": 441,
    "BaseSpeed": 98,
    "UltCost": "140"
  }
]
